odoo/addons/iot/README.rst
odoo/addons/iot/__init__.py
odoo/addons/iot/__manifest__.py
odoo/addons/iot/i18n/es.po
odoo/addons/iot/i18n/iot.pot
odoo/addons/iot/models/__init__.py
odoo/addons/iot/models/iot_device.py
odoo/addons/iot/models/iot_device_action.py
odoo/addons/iot/models/iot_device_group.py
odoo/addons/iot/models/iot_device_tag.py
odoo/addons/iot/models/iot_system.py
odoo/addons/iot/models/iot_system_action.py
odoo/addons/iot/readme/CONTRIBUTORS.rst
odoo/addons/iot/readme/DESCRIPTION.rst
odoo/addons/iot/security/iot_security.xml
odoo/addons/iot/security/ir.model.access.csv
odoo/addons/iot/static/description/icon.png
odoo/addons/iot/static/description/icon.svg
odoo/addons/iot/static/description/index.html
odoo/addons/iot/tests/__init__.py
odoo/addons/iot/tests/test_iot.py
odoo/addons/iot/views/iot_device_group.xml
odoo/addons/iot/views/iot_device_tag.xml
odoo/addons/iot/views/iot_device_views.xml
odoo/addons/iot/views/iot_menu.xml
odoo/addons/iot/views/iot_system_views.xml
odoo12_addon_iot-12.0.1.3.1.dist-info/METADATA
odoo12_addon_iot-12.0.1.3.1.dist-info/WHEEL
odoo12_addon_iot-12.0.1.3.1.dist-info/top_level.txt
odoo12_addon_iot-12.0.1.3.1.dist-info/RECORD
